pyreparse/PyReParse.py
pyreparse/__init__.py
pyreparse/example/__init__.py
pyreparse/example/pyreparse_example.py
pyreparse/tests/__init__.py
pyreparse/tests/test_pyreparse.py
pyreparse-0.0.3.dist-info/METADATA
pyreparse-0.0.3.dist-info/WHEEL
pyreparse-0.0.3.dist-info/licenses/LICENSE
pyreparse-0.0.3.dist-info/RECORD
