Metadata-Version: 2.1
Name: pyreparse
Version: 0.0.3
Summary: Build Efficient RegExp Parsing Engines.
Project-URL: Homepage, https://github.com/dsidlo/pyreparse
Project-URL: Bug Tracker, https://github.com/dsidlo/pyreparse/issues
Author-email: dsidlo <dsidlo@gmail.com>
License:                                  Apache License
Classifier: License :: OSI Approved :: Apache Software License
Classifier: Operating System :: OS Independent
Classifier: Programming Language :: Python :: 3
Classifier: Topic :: Text Processing
Requires-Python: >=3.7
